LICENSE
MANIFEST.in
README.md
setup.cfg
setup.py
faircorels/README.md
faircorels/__init__.py
faircorels/_corels.cpp
faircorels/_corels.pyx
faircorels/corels.py
faircorels/metrics.py
faircorels/utils.py
faircorels.egg-info/PKG-INFO
faircorels.egg-info/SOURCES.txt
faircorels.egg-info/dependency_links.txt
faircorels.egg-info/requires.txt
faircorels.egg-info/top_level.txt
faircorels/src/utils.cpp
faircorels/src/utils.hh
faircorels/src/corels/src/alloc.hh
faircorels/src/corels/src/cache.cpp
faircorels/src/corels/src/cache.hh
faircorels/src/corels/src/corels.cpp
faircorels/src/corels/src/filtering_algorithms.cpp
faircorels/src/corels/src/mistral_backtrack.cpp
faircorels/src/corels/src/mistral_backtrack.hpp
faircorels/src/corels/src/mistral_constraint.cpp
faircorels/src/corels/src/mistral_constraint.hpp
faircorels/src/corels/src/mistral_global.cpp
faircorels/src/corels/src/mistral_global.hpp
faircorels/src/corels/src/mistral_sat.cpp
faircorels/src/corels/src/mistral_sat.hpp
faircorels/src/corels/src/mistral_search.cpp
faircorels/src/corels/src/mistral_search.hpp
faircorels/src/corels/src/mistral_solver.cpp
faircorels/src/corels/src/mistral_solver.hpp
faircorels/src/corels/src/mistral_structure.cpp
faircorels/src/corels/src/mistral_structure.hpp
faircorels/src/corels/src/mistral_variable.cpp
faircorels/src/corels/src/mistral_variable.hpp
faircorels/src/corels/src/pmap.cpp
faircorels/src/corels/src/pmap.hh
faircorels/src/corels/src/queue.hh
faircorels/src/corels/src/rule.hh
faircorels/src/corels/src/rulelib.cpp
faircorels/src/corels/src/run.cpp
faircorels/src/corels/src/run.hh
faircorels/src/corels/src/utils.cpp
faircorels/src/corels/src/utils.hh